{
  "db_name": "SQLite",
  "query": "SELECT status, termination_reason FROM peers WHERE instance_pubkey = ?",
  "describe": {
    "columns": [
      {
        "name": "status",
        "ordinal": 0,
        "type_info": "Text"
      },
      {
        "name": "termination_reason",
        "ordinal": 1,
        "type_info": "Text"
      }
    ],
    "parameters": {
      "Right": 1
    },
    "nullable": [
      false,
      true
    ]
  },
  "hash": "fc6553e2c68f5247ebee9568f0858bafcb8255a222c53f40ca17a4ae060f010e"
}
